flame-stubs/__init__.pyi
flame-stubs/py.typed
types_flame-2024.2.0.dist-info/LICENSE
types_flame-2024.2.0.dist-info/METADATA
types_flame-2024.2.0.dist-info/WHEEL
types_flame-2024.2.0.dist-info/top_level.txt
types_flame-2024.2.0.dist-info/RECORD
