Metadata-Version: 2.1
Name: types-flame
Version: 2024.2.0
Summary: Python stubs for the Autodesk Flame Python API
Author-email: Beat Reichenbach <beatreichenbach@users.noreply.github.com>
Keywords: types,graphics,VFX
Classifier: Programming Language :: Python :: 3
Classifier: Operating System :: OS Independent
Classifier: Intended Audience :: Developers
Classifier: Typing :: Stubs Only
Requires-Python: >=3.9
License-File: LICENSE
Provides-Extra: dev
Requires-Dist: black>=24.0; extra == "dev"
